[{"__type__":"cc.Prefab","_name":"ResultCard_1","data":{"__id__":1}},{"__type__":"cc.Node","_name":"ResultCard_1","_children":[{"__id__":2},{"__id__":3},{"__id__":5}],"_level":4,"_components":[{"__type__":"cc.Sprite","node":{"__id__":1}},{"__type__":"dd61a24U7NPSab4nZxl1OyS","node":{"__id__":1},"cardValue":{"__id__":4},"magicFlag":{"__id__":6},"cardZIndex":101}],"_prefab":{"__type__":"cc.PrefabInfo","root":{"__id__":1},"asset":{"__uuid__":"3ftMIe3VxAT4hQH/TDBa3r"},"fileId":"edW2TtzBZPaqZ4kK8W10iQ"},"_position":{"__type__":"cc.Vec3","x":160.6,"y":-14},"_scale":{"__type__":"cc.Vec3","x":1,"y":1,"z":1}},{"__type__":"cc.Node","_name":"cardBack","_parent":{"__id__":1},"_level":2,"_components":[{"__type__":"cc.Sprite","node":{"__id__":2},"_spriteFrame":{"__uuid__":"79UfC/mrlE/KxxNCI6w++l"},"_sizeMode":2,"_isTrimmedMode":false}],"_prefab":{"__type__":"cc.PrefabInfo","root":{"__id__":1},"asset":{"__uuid__":"3ftMIe3VxAT4hQH/TDBa3r"},"fileId":"8aTELEn71GfIQAbza05PqD"},"_contentSize":{"__type__":"cc.Size","width":132,"height":116},"_scale":{"__type__":"cc.Vec3","x":1,"y":1,"z":1}},{"__type__":"cc.Node","_name":"cardValue","_parent":{"__id__":1},"_level":2,"_components":[{"__id__":4}],"_prefab":{"__type__":"cc.PrefabInfo","root":{"__id__":1},"asset":{"__uuid__":"3ftMIe3VxAT4hQH/TDBa3r"},"fileId":"b8qrBtJ0JBQpWKEL9psH1v"},"_contentSize":{"__type__":"cc.Size","width":86,"height":66},"_position":{"__type__":"cc.Vec3","x":-5.8,"y":16},"_scale":{"__type__":"cc.Vec3","x":1,"y":1,"z":1}},{"__type__":"cc.Sprite","node":{"__id__":3},"_spriteFrame":{"__uuid__":"30k4P13AxD0bR3Z4y+aAuo"},"_sizeMode":2,"_isTrimmedMode":false},{"__type__":"cc.Node","_name":"flag","_parent":{"__id__":1},"_level":2,"_components":[{"__id__":6}],"_prefab":{"__type__":"cc.PrefabInfo","root":{"__id__":1},"asset":{"__uuid__":"3ftMIe3VxAT4hQH/TDBa3r"},"fileId":"384eHj8ZxEqYQ56Wr7wNKj"},"_contentSize":{"__type__":"cc.Size","width":43,"height":29},"_position":{"__type__":"cc.Vec3","x":33.2,"y":40.3},"_scale":{"__type__":"cc.Vec3","x":1,"y":1,"z":1}},{"__type__":"cc.Sprite","node":{"__id__":5},"_spriteFrame":{"__uuid__":"2736+rTotNrpCkuNzUp9Sb"},"_sizeMode":2,"_isTrimmedMode":false}]