[{"__type__":"cc.SpriteFrame","content":{"name":"CardBack_down_8","texture":"76U//OTNFJ5LKKrWm66o5E","rect":[182,80,72,40],"offset":[0,0],"originalSize":[72,40],"capInsets":[0,0,0,0]}},[{"__type__":"cc.Prefab","_name":"ResultCard_8","data":{"__id__":1}},{"__type__":"cc.Node","_name":"ResultCard_8","_children":[{"__id__":2},{"__id__":3}],"_components":[{"__type__":"cc.Sprite","node":{"__id__":1}},{"__type__":"dd61a24U7NPSab4nZxl1OyS","node":{"__id__":1},"cardValue":{"__id__":4},"cardZIndex":192}],"_prefab":{"__type__":"cc.PrefabInfo","root":{"__id__":1},"asset":{"__uuid__":"95JdQrhWhCLqFunuD44/e+"},"fileId":"0fnMmrx3lHyJx6mN2x26xb"},"_trs":{"__type__":"TypedArray","ctor":"Float64Array","array":[-125.9,170,0,0,0,0,1,1,1,1]},"_zIndex":0},{"__type__":"cc.Node","_name":"cardBack","_parent":{"__id__":1},"_components":[{"__type__":"cc.Sprite","node":{"__id__":2},"_spriteFrame":{"__uuid__":"90+zL9kWpBMovVsZjyLY3M"},"_sizeMode":2,"_isTrimmedMode":false}],"_prefab":{"__type__":"cc.PrefabInfo","root":{"__id__":1},"asset":{"__uuid__":"95JdQrhWhCLqFunuD44/e+"},"fileId":"f14t9xgRFJv4n2eIuUQpk5"},"_contentSize":{"__type__":"cc.Size","width":72,"height":40},"_trs":{"__type__":"TypedArray","ctor":"Float64Array","array":[0,0,0,0,0,0,1,-1,1,1]},"_zIndex":0},{"__type__":"cc.Node","_name":"cardValue","_parent":{"__id__":1},"_components":[{"__id__":4}],"_prefab":{"__type__":"cc.PrefabInfo","root":{"__id__":1},"asset":{"__uuid__":"95JdQrhWhCLqFunuD44/e+"},"fileId":"69Uzo99u5NDK7WB/ngOVp3"},"_contentSize":{"__type__":"cc.Size","width":58,"height":20},"_trs":{"__type__":"TypedArray","ctor":"Float64Array","array":[0.8,7.7,0,0,0,0,1,0.82,0.82,1]},"_zIndex":0},{"__type__":"cc.Sprite","node":{"__id__":3},"_spriteFrame":{"__uuid__":"b6aPkwRPNMPJp7tYf2Xi1G"},"_sizeMode":2,"_isTrimmedMode":false}],{"__type__":"cc.SpriteFrame","content":{"name":"CardValue_1","texture":"76U//OTNFJ5LKKrWm66o5E","rect":[2,348,52,20],"offset":[2,0],"originalSize":[58,20],"capInsets":[0,0,0,0]}}]