[{"__type__":"cc.Prefab","_name":"ResultLayer","data":{"__id__":1}},{"__type__":"cc.Node","_name":"ResultLayer","_children":[{"__id__":2}],"_level":1,"_components":[{"__type__":"cc.Layout","node":{"__id__":1},"_layoutSize":{"__type__":"cc.Size","width":1000,"height":500}},{"__type__":"cf1f0W6W61N8oP75/WOaxJ1","node":{"__id__":1},"btn_ready":{"__id__":6},"btn_share":{"__id__":8},"btn_change":{"__id__":10},"nodeResult":{"__id__":3},"nodeMoma":{"__id__":12},"huangEffect":{"__id__":11},"maCardPool":{"__id__":14}}],"_prefab":{"__type__":"cc.PrefabInfo","root":{"__id__":1},"asset":{"__uuid__":"06dx/QzUFCcrSiHFJ+WN3v"},"fileId":"54JQpnLUZJforl99sKm8Jm"},"_contentSize":{"__type__":"cc.Size","width":1000,"height":500},"_scale":{"__type__":"cc.Vec3","x":1,"y":1,"z":1}},{"__type__":"cc.Node","_name":"content","_parent":{"__id__":1},"_children":[{"__id__":3},{"__id__":12}],"_level":2,"_prefab":{"__type__":"cc.PrefabInfo","root":{"__id__":1},"asset":{"__uuid__":"06dx/QzUFCcrSiHFJ+WN3v"},"fileId":"58khOIHLBC4astFAC15Yay"},"_contentSize":{"__type__":"cc.Size","width":1000,"height":500},"_scale":{"__type__":"cc.Vec3","x":1,"y":1,"z":1}},{"__type__":"cc.Node","_name":"ResultNode","_parent":{"__id__":2},"_children":[{"__id__":4},{"__id__":5},{"__id__":7},{"__id__":9},{"__id__":11}],"_active":false,"_level":3,"_prefab":{"__type__":"cc.PrefabInfo","root":{"__id__":1},"asset":{"__uuid__":"06dx/QzUFCcrSiHFJ+WN3v"},"fileId":"49AKvm44tM16CGZqh64qi2"},"_contentSize":{"__type__":"cc.Size","width":1000,"height":500},"_scale":{"__type__":"cc.Vec3","x":1,"y":1,"z":1}},{"__type__":"cc.Node","_name":"bg","_parent":{"__id__":3},"_level":4,"_components":[{"__type__":"cc.Sprite","node":{"__id__":4},"_spriteFrame":{"__uuid__":"cbOiT9uaVK44BooB0ASx7r"}}],"_prefab":{"__type__":"cc.PrefabInfo","root":{"__id__":1},"asset":{"__uuid__":"06dx/QzUFCcrSiHFJ+WN3v"},"fileId":"744JG4y69PzJxjf3XaIEQT"},"_contentSize":{"__type__":"cc.Size","width":1275,"height":157},"_position":{"__type__":"cc.Vec3","y":-202},"_scale":{"__type__":"cc.Vec3","x":1,"y":1,"z":1}},{"__type__":"cc.Node","_name":"btnReady","_parent":{"__id__":3},"_level":4,"_components":[{"__type__":"cc.Sprite","node":{"__id__":5},"_spriteFrame":{"__uuid__":"481eXNiHJG1ql1gk9fTv+z"},"_type":1,"_sizeMode":2,"_isTrimmedMode":false},{"__id__":6}],"_prefab":{"__type__":"cc.PrefabInfo","root":{"__id__":1},"asset":{"__uuid__":"06dx/QzUFCcrSiHFJ+WN3v"},"fileId":"4dZJxMqilNObxyQ8S6OLc8"},"_contentSize":{"__type__":"cc.Size","width":198,"height":86},"_position":{"__type__":"cc.Vec3","x":-240,"y":-202},"_scale":{"__type__":"cc.Vec3","x":1,"y":1,"z":1}},{"__type__":"cc.Button","node":{"__id__":5},"_N$transition":2,"transition":2,"_N$normalColor":{"__type__":"cc.Color","r":255,"g":255,"b":255},"_N$pressedColor":{"__type__":"cc.Color","r":255,"g":255,"b":255},"pressedColor":{"__type__":"cc.Color","r":255,"g":255,"b":255},"_N$disabledColor":{"__type__":"cc.Color","r":255,"g":255,"b":255},"_N$normalSprite":{"__uuid__":"481eXNiHJG1ql1gk9fTv+z"},"_N$pressedSprite":{"__uuid__":"04o8P4eHFGd5dlAVGqipC6"},"pressedSprite":{"__uuid__":"04o8P4eHFGd5dlAVGqipC6"},"_N$hoverSprite":{"__uuid__":"481eXNiHJG1ql1gk9fTv+z"},"hoverSprite":{"__uuid__":"481eXNiHJG1ql1gk9fTv+z"},"_N$disabledSprite":{"__uuid__":"481eXNiHJG1ql1gk9fTv+z"},"_N$target":{"__id__":5}},{"__type__":"cc.Node","_name":"btnShare","_parent":{"__id__":3},"_level":4,"_components":[{"__type__":"cc.Sprite","node":{"__id__":7},"_spriteFrame":{"__uuid__":"c7KgYeFu9Kx7vY4ZZq4eub"},"_type":1,"_sizeMode":2,"_isTrimmedMode":false},{"__id__":8}],"_prefab":{"__type__":"cc.PrefabInfo","root":{"__id__":1},"asset":{"__uuid__":"06dx/QzUFCcrSiHFJ+WN3v"},"fileId":"10fl/hW7xByLMSkpKcNLOS"},"_contentSize":{"__type__":"cc.Size","width":198,"height":86},"_position":{"__type__":"cc.Vec3","y":-202},"_scale":{"__type__":"cc.Vec3","x":1,"y":1,"z":1}},{"__type__":"cc.Button","node":{"__id__":7},"_N$transition":2,"transition":2,"_N$normalColor":{"__type__":"cc.Color","r":255,"g":255,"b":255},"_N$pressedColor":{"__type__":"cc.Color","r":255,"g":255,"b":255},"pressedColor":{"__type__":"cc.Color","r":255,"g":255,"b":255},"_N$disabledColor":{"__type__":"cc.Color","r":255,"g":255,"b":255},"_N$normalSprite":{"__uuid__":"c7KgYeFu9Kx7vY4ZZq4eub"},"_N$pressedSprite":{"__uuid__":"9fD94El41GuIKk+sMWm+6o"},"pressedSprite":{"__uuid__":"9fD94El41GuIKk+sMWm+6o"},"_N$hoverSprite":{"__uuid__":"c7KgYeFu9Kx7vY4ZZq4eub"},"hoverSprite":{"__uuid__":"c7KgYeFu9Kx7vY4ZZq4eub"},"_N$disabledSprite":{"__uuid__":"c7KgYeFu9Kx7vY4ZZq4eub"},"_N$target":{"__id__":7}},{"__type__":"cc.Node","_name":"btnChange","_parent":{"__id__":3},"_level":4,"_components":[{"__type__":"cc.Sprite","node":{"__id__":9},"_spriteFrame":{"__uuid__":"b8sR1olf5GI7HplQuWpwBP"},"_type":1,"_sizeMode":2,"_isTrimmedMode":false},{"__id__":10}],"_prefab":{"__type__":"cc.PrefabInfo","root":{"__id__":1},"asset":{"__uuid__":"06dx/QzUFCcrSiHFJ+WN3v"},"fileId":"8a6DKY5SNNl6iHEieu4+n8"},"_contentSize":{"__type__":"cc.Size","width":198,"height":86},"_position":{"__type__":"cc.Vec3","x":240,"y":-202},"_scale":{"__type__":"cc.Vec3","x":1,"y":1,"z":1}},{"__type__":"cc.Button","node":{"__id__":9},"_N$transition":2,"transition":2,"_N$normalColor":{"__type__":"cc.Color","r":255,"g":255,"b":255},"_N$pressedColor":{"__type__":"cc.Color","r":255,"g":255,"b":255},"pressedColor":{"__type__":"cc.Color","r":255,"g":255,"b":255},"_N$disabledColor":{"__type__":"cc.Color","r":255,"g":255,"b":255},"_N$normalSprite":{"__uuid__":"b8sR1olf5GI7HplQuWpwBP"},"_N$pressedSprite":{"__uuid__":"eaRojH+QFEyqt2xJbcnlSk"},"pressedSprite":{"__uuid__":"eaRojH+QFEyqt2xJbcnlSk"},"_N$hoverSprite":{"__uuid__":"b8sR1olf5GI7HplQuWpwBP"},"hoverSprite":{"__uuid__":"b8sR1olf5GI7HplQuWpwBP"},"_N$disabledSprite":{"__uuid__":"b8sR1olf5GI7HplQuWpwBP"},"_N$target":{"__id__":9}},{"__type__":"cc.Node","_name":"huang","_parent":{"__id__":3},"_level":4,"_components":[{"__type__":"cc.Sprite","node":{"__id__":11},"_spriteFrame":{"__uuid__":"9for4+i3NFPLnNpW58mBm5"}}],"_prefab":{"__type__":"cc.PrefabInfo","root":{"__id__":1},"asset":{"__uuid__":"06dx/QzUFCcrSiHFJ+WN3v"},"fileId":"5dgVG3rm1GPJb9YmgEY2s4"},"_contentSize":{"__type__":"cc.Size","width":1037,"height":569},"_position":{"__type__":"cc.Vec3","y":62},"_scale":{"__type__":"cc.Vec3","x":1,"y":1,"z":1}},{"__type__":"cc.Node","_name":"MoMaNode","_parent":{"__id__":2},"_children":[{"__id__":13}],"_active":false,"_level":3,"_prefab":{"__type__":"cc.PrefabInfo","root":{"__id__":1},"asset":{"__uuid__":"06dx/QzUFCcrSiHFJ+WN3v"},"fileId":"52+Cu5Fq9MzLbKRqoKtNaf"},"_contentSize":{"__type__":"cc.Size","width":1000,"height":500},"_scale":{"__type__":"cc.Vec3","x":1,"y":1,"z":1}},{"__type__":"cc.Node","_name":"img_bg","_parent":{"__id__":12},"_children":[{"__id__":14}],"_level":4,"_components":[{"__type__":"cc.Sprite","node":{"__id__":13},"_spriteFrame":{"__uuid__":"07upOyDI5MU5g3PVPR6/V/"},"_type":1,"_sizeMode":0}],"_prefab":{"__type__":"cc.PrefabInfo","root":{"__id__":1},"asset":{"__uuid__":"06dx/QzUFCcrSiHFJ+WN3v"},"fileId":"a2NXGUyn9HsKeVHCkmpmcv"},"_contentSize":{"__type__":"cc.Size","width":200,"height":169},"_scale":{"__type__":"cc.Vec3","x":1,"y":1,"z":1}},{"__type__":"cc.Node","_name":"maCardNode","_parent":{"__id__":13},"_level":5,"_components":[{"__type__":"cc.Widget","node":{"__id__":14},"_alignFlags":8,"_left":131}],"_prefab":{"__type__":"cc.PrefabInfo","root":{"__id__":1},"asset":{"__uuid__":"06dx/QzUFCcrSiHFJ+WN3v"},"fileId":"bcqK7/EO1CTb8gBQxJiY5E"},"_position":{"__type__":"cc.Vec3","x":31},"_scale":{"__type__":"cc.Vec3","x":1,"y":1,"z":1}}]