{"__type__":"cc.JsonAsset","_name":"GamelistConfig","json":{"engine":"Creator","version":"1.0.1","Kind":"游戏ID","Name":"游戏名字","Position":"游戏图标所在位置","Type":"游戏图标类型（1 大图标， 2 上方小图标  3 下方小图标）","Enable":"游戏是否可用（如果现实图标，单游戏未开启可用此项控制）","info":[{"Kind":10100001,"Name":"斗地主","Position":2,"Type":2,"Enable":true},{"Kind":10200004,"Name":"疯狂三张","Position":2,"Type":3,"Enable":true},{"Kind":10200001,"Name":"八人牛牛","Position":1,"Type":1,"Enable":true},{"Kind":20100004,"Name":"百人牛牛","Position":3,"Type":2,"Enable":true},{"Kind":20100001,"Name":"30秒","Position":3,"Type":3,"Enable":true},{"Kind":20100003,"Name":"红黑大战","Position":4,"Type":1,"Enable":true},{"Kind":20100002,"Name":"龙虎斗","Position":5,"Type":2,"Enable":true},{"Kind":40100001,"Name":"广东麻将","Position":5,"Type":3,"Enable":true},{"Kind":30100001,"Name":"捕鱼达人","Position":6,"Type":2,"Enable":true},{"Kind":20200001,"Name":"飞禽走兽","Position":6,"Type":3,"Enable":true},{"Kind":30200001,"Name":"豪华水果连线","Position":7,"Type":2,"Enable":true},{"Kind":10200003,"Name":"德州扑克","Position":8,"Type":1,"Enable":true},{"Kind":20100006,"Name":"百人骰宝","Position":9,"Type":2,"Enable":true},{"Kind":40100002,"Name":"红中麻将","Position":9,"Type":3,"Enable":true},{"Kind":10200005,"Name":"港式五张","Position":10,"Type":1,"Enable":true},{"Kind":30200002,"Name":"水果玛丽","Position":11,"Type":2,"Enable":true},{"Kind":10200009,"Name":"浙江十三水","Position":11,"Type":3,"Enable":true},{"Kind":40100003,"Name":"血战麻将","Position":12,"Type":1,"Enable":true},{"Kind":20100007,"Name":"百人德州","Position":13,"Type":1,"Enable":true},{"Kind":10200006,"Name":"4人牌九","Position":14,"Type":1,"Enable":true},{"Kind":20100009,"Name":"百人二八杠","Position":15,"Type":1,"Enable":true},{"Kind":20300001,"Name":"红包扫雷","Position":10,"Type":3,"Enable":true},{"Kind":10200007,"Name":"推筒子","Position":10,"Type":3,"Enable":true},{"Kind":30100002,"Name":"海王捕鱼","Position":10,"Type":3,"Enable":true},{"Kind":10200002,"Name":"三公","Position":10,"Type":2,"Enable":true}]}}