{"__type__":"cc.SpriteAtlas","_spriteFrames":{"fruits_frame_jackpot2":{"__uuid__":"adKsSOVHxK+KfnuVprCa2r"},"fruits_frame_jackpot":{"__uuid__":"f3esGnrNlMZZCYv8RjeF/x"},"fruits_frame_2":{"__uuid__":"42bwPNj9hHJJwN9c0Ak6zN"},"fruits_btn_turnselect4":{"__uuid__":"70jD2IdqtB2YCiBa8drE48"},"quan_00004":{"__uuid__":"9fbzsbELlD0o4LeEah7n8b"},"fs_1":{"__uuid__":"2d0v/MvkZLLaLpnN5Z4hj3"},"account_uibg":{"__uuid__":"0emdHFErhNx71p6/YucJc2"},"fruits_frame_free2":{"__uuid__":"52ko188hNElK3bw/tKAgEa"},"fruits_frame_bet":{"__uuid__":"8e6705H6tEJbbydVcCcqdL"},"fruits_frame_line":{"__uuid__":"97wD/BoylMa5QU4l7lsmbe"},"fruits_ui_num2":{"__uuid__":"2fTHgXnN9PbZF3AmUmPMe3"},"bw_3":{"__uuid__":"61LM5tWz5JdrtUl2zY13Oa"},"fruits_frame_win1":{"__uuid__":"59xA+iaxRJ+KGX9kmQ52tH"},"goldbg":{"__uuid__":"379uPT/SxE9oR/nHGVaBp0"},"zuanshi":{"__uuid__":"3bii8tZh1LhaT3DP8qqlU/"},"UI_Fruits_ScoreWinbox":{"__uuid__":"b5DcLkXoxDPYscmmOE3v/k"},"fruits_btn_turnselect1":{"__uuid__":"d08RRzZa1BhaBG0ELjRqCv"},"fruits_ui_num1":{"__uuid__":"8bQS3uIFlI+5h5OXu71NVR"},"fruits_frame_win":{"__uuid__":"36enC65LRL4q1lRgl3AIuM"},"fruits_frame_maxbet":{"__uuid__":"4f4u8xNMNDDLZ9On80rEGx"},"account_ui2_2":{"__uuid__":"9fXCqgOxxJVp81kjAO2iuM"},"account_ui2_1":{"__uuid__":"3e0oYV4mxHsoohpv5MlGIL"},"fruits_frame_free":{"__uuid__":"ddP87Sxn1LOJi5o6DWirKh"},"fruits_btn_turnselect3":{"__uuid__":"0ePnDD5VVKLJ+nivwwkdYf"},"guangyun_00000":{"__uuid__":"d5JtpvputEoaQoyS2XKGND"},"fruits_ui_numfree":{"__uuid__":"45ofdKZthIUpOxhtZFXLhs"},"account_ui2":{"__uuid__":"74c4058tlDBI/f5WJsZBEl"},"account_ui3":{"__uuid__":"32zihAzL5IzpML1vYQCYxL"},"fruits_set_gold":{"__uuid__":"f3M7bYDz5FxIInTMZdROva"},"fruits_btn_turnselect2":{"__uuid__":"a4+frWCDlIf7tKcUW48OUZ"},"fruits_ui_numj":{"__uuid__":"c2cdzT7b5Ji5ECosck9Rl0"},"fruits_frame_jackpot3":{"__uuid__":"4eqiVKImVMfqmnZmGOI1mh"},"goldbg_other":{"__uuid__":"88dU2NE6lGEpdPPtlfLBum"},"fruits_btn_rule":{"__uuid__":"04oykUdZdBhJo1H+5wyDk0"},"slot_icon_fruit_w1":{"__uuid__":"5f5U9aMbhIHa2AQWvxAEdC"},"fbyx1":{"__uuid__":"667R2ximtAoaorp9AWl/Nq"},"account_btn_ok":{"__uuid__":"3bHEjOw2lK+rDVGopuRY4X"},"bw_2":{"__uuid__":"9ePmAd5UZN27sfaFzCVgrh"},"slot_icon_fruit_u1":{"__uuid__":"3cICAiYE5CpquV+Y1pXIQ1"},"fruits_frame_bl":{"__uuid__":"0dp6Bx8YBEupjiB+ueaBGw"},"fbyx2":{"__uuid__":"96G2Y6AqpAoJ9+GwM6NOvN"},"bw_1":{"__uuid__":"1f9+u7rJFPmI78illTPXBa"},"fruits_btn_turnoff4":{"__uuid__":"04fSkLIa5IzKkKoAJ15Sev"},"fruits_btn_turnon2":{"__uuid__":"07p82UhyVFe51cFx3ROY4C"},"fruits_btn_turnon3":{"__uuid__":"0eB4tlKV9GRK9Yi0ys6w17"},"fruits_btn_maxbet0":{"__uuid__":"22oN6V8NxF5qwQnSNljI65"},"fruits_btn_maxbet":{"__uuid__":"30qa+gsYpPI6Xb/Uuqk6Mg"},"fruits_btn_turnon":{"__uuid__":"11kOwT6T9L2IDEwJZQp/XM"},"fruits_btn_turnonstop1":{"__uuid__":"43M+D/o5hBALgZzdGSUQV3"},"fruits_btn_turnonstop2":{"__uuid__":"6fQxhb7xxPEbDXLi4HBERa"},"fruits_btn_turnoff3":{"__uuid__":"a9R2M7KG5LZq8LJhnKndwW"},"fruits_btn_turnoff":{"__uuid__":"c4b5IVZmFET6r+8V0iiu95"},"fruits_btn_turnoff2":{"__uuid__":"f6wfioSnJCm64k6x99cVHf"},"slot_icon_fruit_f":{"__uuid__":"f4mnX4hiRLAIw82cnaQ6Uz"},"fruits_btn_maxbet2":{"__uuid__":"3aTsUKv+FIIpiwuPC4P7nO"},"slot_icon_fruit_z1":{"__uuid__":"1ajijl4mtIy6fBUEKPaxLT"},"slot_icon_fruit_u":{"__uuid__":"18xMdpDu9EKK0GCIceSRha"},"account_ui1":{"__uuid__":"2dgEiUE2FGDJn5RT/3+MHL"},"slot_icon_fruit_c1":{"__uuid__":"f1l1LQAxBHvbQpTx/mCacb"},"head_bk":{"__uuid__":"abc7vIwPhKhLtGXwOCMT3t"},"slot_icon_fruit_d1":{"__uuid__":"44cgiNui5FsZnh0JKePSXv"},"slot_icon_fruit_e1":{"__uuid__":"e1aE+VBHFCUZDaStDFOfOU"},"slot_icon_fruit_a1":{"__uuid__":"3fmY+b+eVMJI44kmhYKcGT"},"fruits_btn_rule2":{"__uuid__":"9cq03563tPgI/LnZk6aR56"},"fruits_btn_bladd2":{"__uuid__":"2aBzce8AxGBawZXVp2l3RF"},"bw_4":{"__uuid__":"74G10zgopCSLIyB3owGae7"},"slot_icon_fruit_f1":{"__uuid__":"b7bXc0ikxOSrrfHoK0w46X"},"slot_icon_fruit_b1":{"__uuid__":"f646FJ59JKWoQqJMLe7/F1"},"slot_icon_fruit_s1":{"__uuid__":"de7bKVgvlBzY3GTRlLkbsc"},"fruits_btn_more":{"__uuid__":"3a7fsdCG5DW7fShbvZRI54"},"fruits_btn_back2":{"__uuid__":"64cjiJqddK9obYat14i2bw"},"account_ui4":{"__uuid__":"22zEXg3gBP67QrRg0e/sZ+"},"fx2":{"__uuid__":"67RWjmDZVMNpfMtt2qSRod"},"slot_icon_fruit_g":{"__uuid__":"0dyUzwBC9CcL28yWYG7ODY"},"fruits_btn_bladd0":{"__uuid__":"92IsX9HyNGxZ5ZMDYsoUJm"},"fruits_btn_bladd":{"__uuid__":"bahL8NhapJDIg0VV40s+jg"},"fruits_btn_blmin":{"__uuid__":"68p7ZEC25LtZu1KIA+NDE3"},"slot_icon_fruit_z":{"__uuid__":"02N194cx9LSpxBGYgdHnGc"},"fruits_btn_more2":{"__uuid__":"e7KSBkOW5OVYe9Q0SH/oyi"},"fruits_btn_back":{"__uuid__":"edzsHpWj9NKLWongjU3lzL"},"fruits_btn_blmin2":{"__uuid__":"deYUm9kqxN/6bF71Hl9fdV"},"slot_icon_fruit_g1":{"__uuid__":"0fY0YC3YhAgIjdv/jNt+0N"},"fruits_frame_player":{"__uuid__":"0aUfc7QsRDUqhIX/h2wf5n"},"slot_icon_fruit_w":{"__uuid__":"958stJKAdAz5dCj62pqz9O"},"slot_icon_fruit_c":{"__uuid__":"2c/9xYAnZM2qSOt6QjCjMl"},"slot_icon_fruit_b":{"__uuid__":"b5HGH8v6lIsYDD+0WknUoP"},"slot_icon_fruit_d":{"__uuid__":"47IFl6WsZMYIuNjSFzXNwJ"},"slot_icon_fruit_e":{"__uuid__":"36A7M4aGdLrrl1Ox4VsHVn"},"slot_icon_fruit_s":{"__uuid__":"0a091Ji1lIl5rBJgiiLKIa"},"slot_icon_fruit_a":{"__uuid__":"2e+ljQu5hGsbk7KzGUbHv8"},"fruits_btn_blmin0":{"__uuid__":"e8JQCCrgFBvKbtbOfkp0sQ"}}}