{"__type__":"cc.SpriteAtlas","_spriteFrames":{"cardTxtX41_0":{"__uuid__":"0dpy0qCVNL/4s3V1SI7vY/"},"cardTxtX41_F":{"__uuid__":"17U/2aVTNOsK79R42cjvXL"},"cardTxtX41_2":{"__uuid__":"20OiY9ImNBG6zYcxbR223y"},"cardTxtX41_D":{"__uuid__":"a7ygG0MY9FwoRBKKsZLW7Q"},"cardTxtX41_1":{"__uuid__":"a8sL+OZ81HDqJ2QEFFx3f8"},"cardTxtX41_E":{"__uuid__":"b1TrwSr3lNDrR7z6GDa/yR"},"cardTxtX35_F":{"__uuid__":"95x7UKx69LNJkN/UnySOER"},"cardTxtX35_D":{"__uuid__":"abwbgNbotPI6gYPbMAbaMp"},"cardTxtX35_E":{"__uuid__":"d0GEDYUidKapb/Bt1N3b2T"},"cardTxtX25_0":{"__uuid__":"07910OIY1LA6nNMxnrPSqU"},"cardTxtX18_B":{"__uuid__":"11E+trVupFCquRbHMKjlO+"},"cardTxtX18_A":{"__uuid__":"72pK147tdOMKlMkm808wMu"},"cardTxtX25_1":{"__uuid__":"14cix+1ANHoY6j5BGQE6um"},"cardTxtX25_2":{"__uuid__":"cddrFL3SVGiKWbooTtYxhy"},"cardTxtX21_E":{"__uuid__":"06mRRMZnpFzasbWRAcnii3"},"cardTxtX21_F":{"__uuid__":"33IaXsl0lLyYjTBdnzG2ev"},"cardTxtX35_B":{"__uuid__":"6dwNouYUJKaqeTIMhfCBCt"},"cardTxtX36_4":{"__uuid__":"258ySjxZpOhoXooGnkWiSe"},"cardTxtX21_1":{"__uuid__":"83QuI4DRRO9I3p/VBudfoY"},"cardTxtX21_D":{"__uuid__":"8amkkdww1MX4naULLP/QfP"},"cardTxtX21_2":{"__uuid__":"8cEhztWxlJrZIO9SdV/EPA"},"cardTxtX21_0":{"__uuid__":"bf8G9D0gdIPZE4v2UTAyrD"},"cardTxtX35_C":{"__uuid__":"63oRbNm1BBw6YFVUsiHvrK"},"cardTxtX41_C":{"__uuid__":"220nExH8JLnL4TVyrujL2V"},"cardTxtX41_3":{"__uuid__":"80EbCfiMZMBYhA8dLO2YTz"},"cardTxtX24_1":{"__uuid__":"2epNSmYGpDnKgWcA2L9Rh7"},"cardTxtX24_F":{"__uuid__":"5552Cz8TVCj5MHG6bCWfYv"},"cardTxtX25_E":{"__uuid__":"78HBAqXghNOZsnFN1XF6dP"},"cardTxtX24_E":{"__uuid__":"79r6Scb2JDm7B6ZEJwfDvt"},"cardTxtX25_F":{"__uuid__":"c0ZeP8sOFFQ5OyEc+7DP+V"},"cardTxtX25_D":{"__uuid__":"f1v38Cq0RDpbvmAMDOR0db"},"cardTxtX24_0":{"__uuid__":"feXz+EENpP9JESMX9rQlUz"},"cardTxtX39_2":{"__uuid__":"008V575F5AyYYMn/zjB7rB"},"cardTxtX18_8":{"__uuid__":"30MjtyKZtKcYcqAqkacUTh"},"cardTxtX39_D":{"__uuid__":"53r04IRq1KWpOgWqqG9P15"},"cardTxtX24_2":{"__uuid__":"33TwEwrHhMSIfzKIgB/7tB"},"cardTxtX24_D":{"__uuid__":"c1wu+cYtZMI5iONIOPV0px"},"cardTxtX25_3":{"__uuid__":"e0pSfmZhNLSbGJQ8iVYY4R"},"cardTxtX21_3":{"__uuid__":"0exqfPlgFCVZMF7V+K7+an"},"cardTxtX22_1":{"__uuid__":"1dQKc4RVFJnpbRRSMw/c9R"},"cardTxtX39_0":{"__uuid__":"63pKSSmOJE3pRHwkgwe8ss"},"cardTxtX41_4":{"__uuid__":"62mn8OkEFCWKwx+GBeWiot"},"cardTxtX22_F":{"__uuid__":"65BX0YwFFEDaTD3OnJI680"},"cardTxtX39_C":{"__uuid__":"6e6WmYJe1N74JGi1gu/zy4"},"cardTxtX22_0":{"__uuid__":"c29OOrSHZMIL1IYgGXer/d"},"cardTxtX22_E":{"__uuid__":"e74ZG5CT5E57zuy3mqW0CQ"},"cardTxtX39_1":{"__uuid__":"eas50xGR5HApKv3l3IGvjz"},"cardTxtX41_B":{"__uuid__":"bbFJOOHZ9D+obKQbDNctsy"},"cardTxtX8_0":{"__uuid__":"34ZosT8edJsoE1thkWc2mY"},"cardTxtX8_2":{"__uuid__":"65TCobizRANLjpF2QSjivv"},"cardTxtX8_1":{"__uuid__":"af/6n0DoVA7qFDf6UFECMR"},"cardTxtX24_3":{"__uuid__":"8d7iIpMA5MlILntrJo9GpL"},"cardTxtX25_C":{"__uuid__":"aaPjSHPp5CZLo+m0xhvc+z"},"cardTxtX39_3":{"__uuid__":"175WMv9JFF6J8ZB0YRSUv/"},"cardTxtX22_2":{"__uuid__":"30KrgdjupMrryrpIF67cGK"},"cardTxtX39_F":{"__uuid__":"4es+r2MEBIVIUKfIRPeEOG"},"cardTxtX35_A":{"__uuid__":"c4jqk1wY5BmIl+vRrtBP3s"},"cardTxtX21_C":{"__uuid__":"755wMkig5AzoV32Q6c5RqW"},"cardTxtX39_E":{"__uuid__":"8dGGQUEGFAv5U1XuqgFhve"},"cardTxtX36_D":{"__uuid__":"65oBUqI5xNiL/h/idrCWrs"},"cardTxtX3_0":{"__uuid__":"0bGjlChmtGrqeEcvqGecxj"},"cardTxtX34_7":{"__uuid__":"30K59Ddm1G4ItJwD4AghNZ"},"cardTxtX6_2":{"__uuid__":"0f95IgMDNE3IdvXuAE6OBQ"},"cardTxtX18_1":{"__uuid__":"61YAylvaREHqqwOPra2CW0"},"cardTxtX18_E":{"__uuid__":"74k2paeh5LFoCSLDizJWCS"},"cardTxtX3_2":{"__uuid__":"32buAikCxIraIFFIlYgn53"},"cardTxtX6_1":{"__uuid__":"7e26iI6atGBZEbGNZu8fRs"},"cardTxtX6_0":{"__uuid__":"a9XRyV4rFG/bI2BGvyNUXY"},"cardTxtX3_1":{"__uuid__":"d3blrN+dtHo5OcaOSB07w2"},"cardTxtX33_3":{"__uuid__":"127OcmNmFPu6hFAksRGfcI"},"cardTxtX33_C":{"__uuid__":"11KGXaBi1DEZbWXuHIIx1K"},"cardTxtX8_3":{"__uuid__":"ac8ZvfGH1L5ozOr/66ZGrT"},"cardTxtX17_2":{"__uuid__":"14xCexltBH45wyJG6ozENe"},"cardTxtX17_3":{"__uuid__":"d3Ep5B1gxJjZDhA8ZMyTuW"},"cardTxtX24_C":{"__uuid__":"ebercUEGhMo6z/7P395pzX"},"cardTxtX39_A":{"__uuid__":"6bNmz8VfBKY7I+b5OJ3N7d"},"cardTxtX39_B":{"__uuid__":"ba8Z+EBCVCob9JGqEZv5T4"},"cardTxtX22_D":{"__uuid__":"f9QYBGTyBBqagiQ3DJY5xb"},"cardTxtX6_3":{"__uuid__":"021VsdNZlIsLYwKZmP0s1C"},"cardTxtX3_F":{"__uuid__":"3c2Rkf6zVL0r+jnP2MULqn"},"cardTxtX18_7":{"__uuid__":"5cyISXKIZLe5JnpT8R1hdj"},"cardTxtX3_3":{"__uuid__":"77jkhjIHRLULT/i369MFiH"},"cardTxtX3_E":{"__uuid__":"80LXJYSsREzJiXd1F6WADW"},"cardTxtX36_1":{"__uuid__":"01O8rRozhCZ5IOKmXOFRtm"},"cardTxtX3_D":{"__uuid__":"b9vRvoSE9AwaUHs9v+j3XI"},"cardTxtX41_5":{"__uuid__":"a6ajCkhXBN2LoZU1UUNXqt"},"cardTxtX41_A":{"__uuid__":"c3GhneHzJNHp3SLpQgBlm/"},"cardTxtX4_2":{"__uuid__":"33CMFLcRVNKp63eJitexPx"},"cardTxtX4_1":{"__uuid__":"752jwWgcJHT5m4GsCUhMlu"},"cardTxtX4_0":{"__uuid__":"e9qM9SU7FA5rLoYfa9TIAi"},"cardTxtX7_2":{"__uuid__":"ecnJP6rytFgJMVP/0glmmq"},"cardTxtX25_4":{"__uuid__":"8a2Dw8A4tGwblTXpKBkkqs"},"cardTxtX17_0":{"__uuid__":"64TkDOASdN9YULyiqzdnEL"},"cardTxtX18_F":{"__uuid__":"c4mgKdXcpKEYXacZbFnMJB"},"cardTxtX2_2":{"__uuid__":"7fqRTUEVpCIriiozPYdVO8"},"cardTxtX17_1":{"__uuid__":"aeYPnHOxRJMoLplkMMTZx7"},"cardTxtX2_1":{"__uuid__":"c2VMcoxRtMLZBa03Q91BLT"},"cardTxtX36_0":{"__uuid__":"33T8iKD6BEHIQr9zRYTWLd"},"cardTxtX2_0":{"__uuid__":"efClbhKuxC079O+ELSFZmk"},"cardTxtX17_5":{"__uuid__":"f9s6NNcGhDsZkosb3UbzL+"},"cardTxtX22_3":{"__uuid__":"329FLFgntLCId8RfawleT0"},"cardTxtX39_9":{"__uuid__":"3fXVNW9rZKmZPmqh6hCaEU"},"cardTxtX21_4":{"__uuid__":"a4Q2NFaBNCioCaD34D/JA5"},"cardTxtX22_C":{"__uuid__":"b2dNCtSgNPAJvY52XeSS5U"},"cardTxtX21_B":{"__uuid__":"c4Pw2U679GS5bXmGlDPDeq"},"cardTxtX39_4":{"__uuid__":"e5UCHNlBZBFqJSv9vKBa9h"},"cardTxtX3_4":{"__uuid__":"22BhSboGdBabERbcEMzsfD"},"cardTxtX9_2":{"__uuid__":"77uAeybYNDzZHHPgsC7JvV"},"cardTxtX6_F":{"__uuid__":"7bGbS8celNIIqbNHaPZ+yt"},"cardTxtX8_4":{"__uuid__":"995cp5RzNLMIBU5xXa3K0l"},"cardTxtX6_E":{"__uuid__":"b7yKN4ZVdAB7CgobNEE1RR"},"cardTxtX6_D":{"__uuid__":"cdo6FGd7ZL2IDcIkd03Jxs"},"cardTxtX5_E":{"__uuid__":"44Zp3PtzFM6p2YMpj3sVrg"},"cardTxtX5_D":{"__uuid__":"4bWtf4NmVN64XHsjYh/7Wj"},"cardTxtX7_1":{"__uuid__":"6e/7xO+TVM8Jr8/TuW4aUw"},"cardTxtX5_F":{"__uuid__":"91QMSDyXBFeZHH8Y+kSi69"},"cardTxtX7_0":{"__uuid__":"a89ks0YVVEJ7jkG3Nx46HD"},"cardTxtX17_6":{"__uuid__":"a3S84EnpZGmZ4MFYvS47in"},"cardTxtX17_4":{"__uuid__":"dbtRoOTWlAppidVdZYSH0w"},"cardTxtX36_F":{"__uuid__":"35iesve51FnJGAgoqjRty+"},"cardTxtX36_2":{"__uuid__":"48TctB+zRPa6Kg3Pz87dhC"},"cardTxtX37_D":{"__uuid__":"57c6lpMjpKsJftlbNVrDM7"},"cardTxtX18_2":{"__uuid__":"fdAcVdeEdCQbPFNd/pSBYR"},"cardTxtX37_E":{"__uuid__":"abrawnoxtKDbqEK6GY9luN"},"cardTxtX37_F":{"__uuid__":"bf97md5WVBJLxJQx4w9yeU"},"cardTxtX36_E":{"__uuid__":"cdjKnLCwZGEah2ADTVSBcz"},"cardTxtX37_2":{"__uuid__":"d3VU2zsZBFYaPAh1ezB2Jr"},"cardTxtX23_2":{"__uuid__":"4bjpCHGbpF17p5K6u9Qc18"},"cardTxtX23_0":{"__uuid__":"88A1itwQRHpIC4erl/QS+9"},"cardTxtX23_C":{"__uuid__":"92yuDPU0JGbZx8Je//7Ub5"},"cardTxtX23_E":{"__uuid__":"93KWbZs5dH8JqjfkRH65Bn"},"cardTxtX23_F":{"__uuid__":"a14qR34BhBCIqa34WktCUf"},"cardTxtX23_1":{"__uuid__":"a5suAlybNMiogbQHIDCYpz"},"cardTxtX25_B":{"__uuid__":"a98sfJ4/FF56pF0mJTf65K"},"cardTxtX23_D":{"__uuid__":"aaZJdPiw1PVLzK969xU4OL"},"cardTxtX24_B":{"__uuid__":"ddxMUvbBdG2bUMvunllYEx"},"cardTxtX39_5":{"__uuid__":"58OK6rt/pJ46NVtUVc20bq"},"cardTxtX39_6":{"__uuid__":"8brJsS0ahJJJlUDMBjJkev"},"cardTxtX39_8":{"__uuid__":"d5Xh2TbetGAK/S694AeiAV"},"cardTxtX21_5":{"__uuid__":"d6QDbW5OZCXLUO1t/3fjuF"},"cardTxtX41_9":{"__uuid__":"96u4On8a9KYoUAqeyUijPJ"},"cardTxtX41_6":{"__uuid__":"e6+IPFLY9EdLHQ8iE8d2z3"},"cardTxtX9_1":{"__uuid__":"1fMe+TpspFLJBXrutNO/mR"},"cardTxtX8_5":{"__uuid__":"5fphz6Hu9BnIVjbarqq1Fx"},"cardTxtX18_0":{"__uuid__":"e50zDXeMtMdr+1u/1cpLeZ"},"cardTxtX6_C":{"__uuid__":"83lvnvPOxLa7Rfbcrob9Wn"},"cardTxtX9_0":{"__uuid__":"a3MiXLoqVGP7LRJx7BsDdG"},"cardTxtX18_5":{"__uuid__":"7fJAHApBtPN7Qm2Y1XbKWL"},"cardTxtX3_C":{"__uuid__":"e4FLbjkHNHZLboSQjlczQW"},"cardTxtX18_D":{"__uuid__":"fek/b/+u9Hn63/FzF6c1/n"},"cardTxtX18_3":{"__uuid__":"a77ZZg3vBMsrTck8jEsbg9"},"cardTxtX18_C":{"__uuid__":"abepXB4B9LzIQw2Y49HGKp"},"cardTxtX18_4":{"__uuid__":"1euFkeTXZCM4AHcyhBJ+Ki"},"cardTxtX18_6":{"__uuid__":"0a/e08gk9FM7U0JmOsVIuf"},"cardTxtX35_9":{"__uuid__":"25wxnixVlIh5LMUDRaELEy"},"cardTxtX4_3":{"__uuid__":"03EW4S0zRBTaJVADiIOFhv"},"cardTxtX36_C":{"__uuid__":"3fGRvtja1HMYHhVdSY6sB+"},"cardTxtX20_8":{"__uuid__":"31fo2g2QFK8Y1/jDMx2gg5"},"cardTxtX18_9":{"__uuid__":"5eHR28atdBwpZdAOxNZbpN"},"cardTxtX33_A":{"__uuid__":"2e6+RgRNhJ4Ls9tQglxg1s"},"cardTxtX4_F":{"__uuid__":"12i3MVcKNJs7MZO98upUMT"},"cardTxtX24_7":{"__uuid__":"0eq/YBLohDA69W3X6s9yUH"},"cardTxtX2_4":{"__uuid__":"8cKS0m0qJBO6+UaVpDzyDZ"},"cardTxtX36_B":{"__uuid__":"59F1sw5ONOqKk0waj4ZZDx"},"cardTxtX36_3":{"__uuid__":"42T09MgBxHhrw7C8/I95ZU"},"cardTxtX33_B":{"__uuid__":"23oN4X92JAsoAMHyFb4DIQ"},"cardTxtX37_1":{"__uuid__":"5bYsgGoClCsrwcXuKIUGsW"},"cardTxtX4_E":{"__uuid__":"a4xOxuz05Gg6wY+/EoEYlB"},"cardTxtX7_3":{"__uuid__":"f0vsSh6sFCdrwSgL4eMg/3"},"cardTxtX37_0":{"__uuid__":"ca5RqegKVDEYZBYsX9hbSS"},"cardTxtX17_9":{"__uuid__":"3eM5H4KgZKw4g+QN3JOi6V"},"cardTxtX2_3":{"__uuid__":"46mp1H/ZpCUY51JCukPlMO"},"cardTxtX17_C":{"__uuid__":"8ctJdghDxO8IMk0bBFlPo0"},"cardTxtX2_E":{"__uuid__":"93hV4d4kNNs5TAiIAJj9CF"},"cardTxtX17_B":{"__uuid__":"a8UQSDJjNBEZKIxSJOj2A0"},"cardTxtX2_C":{"__uuid__":"aboQHLpXFEMIonFGGMpSoQ"},"cardTxtX17_A":{"__uuid__":"b7HgfgJctMMpAVJniilily"},"cardTxtX17_D":{"__uuid__":"b9T8AEaKBFA7ycYduTiz/U"},"cardTxtX2_D":{"__uuid__":"baK6s9rUJN6Zp4WLCaQt1o"},"cardTxtX2_F":{"__uuid__":"ecK2s7IVJLaY4n8csDCh5F"},"cardTxtX25_A":{"__uuid__":"87zB3Tb/NNaIEO67vCqN48"},"cardTxtX25_5":{"__uuid__":"c30odrRr5LYIeOHdUmePq/"},"cardTxtX23_3":{"__uuid__":"ddUehmHW1G16C/TroJylCF"},"cardTxtX24_4":{"__uuid__":"e0qqvszExCwJn9J91vH+8X"},"cardTxtX21_A":{"__uuid__":"14uOspsg1Bq7J1322mwQBe"},"cardTxtX39_7":{"__uuid__":"1afpKM1XJPk4ADzB6W4mg5"},"cardTxtX6_4":{"__uuid__":"1aBLgFU+xKC5rIUKPEomJ/"},"cardTxtX3_5":{"__uuid__":"69ezzthpFD8KS7VxPxS1zi"},"cardTxtX3_B":{"__uuid__":"a7ipe8R/REi7Lht4nHIGIz"},"cardTxtX8_6":{"__uuid__":"b8j49lJWZGBq9I1zuycaFR"},"cardTxtX38_3":{"__uuid__":"38nTu7rJJALaHzQcyl83uh"},"cardTxtX4_4":{"__uuid__":"c2PoRbKFNNsLnPhbn+TWF6"},"cardTxtX9_D":{"__uuid__":"c8Gj0gUCFNeYXreqAhH/YY"},"cardTxtX9_3":{"__uuid__":"dcE1wxXPdATKCKW27tkGoH"},"cardTxtX1_0":{"__uuid__":"46SRmYsIRHOKZWiiSzGfvd"},"cardTxtX1_2":{"__uuid__":"5cOlPMnStBJKv3u4Hzs9Xg"},"cardTxtX38_C":{"__uuid__":"c0zh0Wjg9Lk6WCwWNLvRsm"},"cardTxtX1_1":{"__uuid__":"efUQgp0NNGsrZOS++a6BeE"},"cardTxtX37_3":{"__uuid__":"2azmezWhBKmI+zsM0d/aPG"},"cardTxtX37_C":{"__uuid__":"90a6byGzZFHJQNCuJ6gA6N"},"cardTxtX4_D":{"__uuid__":"01WhTDjOpCk5t+W+PQQ+LB"},"cardTxtX40_0":{"__uuid__":"25TNVwinlEOKa9uKM/wa8b"},"cardTxtX40_E":{"__uuid__":"2bMgmZXbdHUZ7gk4xqLNUX"},"cardTxtX40_1":{"__uuid__":"52dc3OSvBNaL0y9Jz4WA6/"},"cardTxtX5_C":{"__uuid__":"59cWIf0UNOyb7bcII1wugn"},"cardTxtX40_2":{"__uuid__":"86pQWLFKdLbZV9bZIQwt7x"},"cardTxtX2_5":{"__uuid__":"c21F0CqkdFfKQhzRshJEM0"},"cardTxtX40_F":{"__uuid__":"e0LoTE4yVIrZi4vjgjQFJB"},"cardTxtX17_8":{"__uuid__":"9doWIpHJxMy6COWukp8r+q"},"cardTxtX17_7":{"__uuid__":"b76bQDs8FBQKVcdBzud5FN"},"cardTxtX38_2":{"__uuid__":"32OS8c5rtCGK+ojsMovWKg"},"cardTxtX38_D":{"__uuid__":"532MRstTNLn5EaMl+x5Mdl"},"cardTxtX38_1":{"__uuid__":"60yku36hhA37fQDZTubLZT"},"cardTxtX38_0":{"__uuid__":"81nTh/BdtJYalOW/re2uJq"},"cardTxtX38_E":{"__uuid__":"96OG8C7qFE/L/2HDF39yUf"},"cardTxtX38_F":{"__uuid__":"f1T+DQLH1Ly6lOtPyOku6E"},"cardTxtX23_4":{"__uuid__":"77BQpJBIFFgop/afP7ggzh"},"cardTxtX22_B":{"__uuid__":"667itpu7tCw5YdkALhIlsG"},"cardTxtX22_4":{"__uuid__":"94vX5zADRPppFnRGhv3GLT"},"cardTxtX41_7":{"__uuid__":"76tS8a4+BEMYa1ET1cjtA0"},"cardTxtX1_3":{"__uuid__":"a02O0Ma2BCh67gF/FBFQU1"},"cardTxtX41_8":{"__uuid__":"32oZDKBf5F6K1jNtjojKH9"},"cardTxtX9_B":{"__uuid__":"08korp7t9Az70g3K/ytCOi"},"cardTxtX5_B":{"__uuid__":"16UGQ1bvdFCayB3hTpX/Vy"},"cardTxtX5_A":{"__uuid__":"1di/XxfJdMMqX8iPJHRpdo"},"cardTxtX9_C":{"__uuid__":"37cr4xolpPlb840+fW1X55"},"cardTxtX36_5":{"__uuid__":"60d44cGJ9MaKyiEyJALddA"},"cardTxtX8_A":{"__uuid__":"56EQTmEaVGVrwWKUyUO7fS"},"cardTxtX9_4":{"__uuid__":"6bMJGODb9PsrSSq8CwuJk7"},"cardTxtX6_9":{"__uuid__":"8eCCjoFPtA6IZ7J6w5OztJ"},"cardTxtX3_6":{"__uuid__":"93Ag/ADUNPiqWiVdxjLpLq"},"cardTxtX4_5":{"__uuid__":"b2OSGR5aRC+6kSY7+aCmqT"},"cardTxtX6_5":{"__uuid__":"b2sUdcgaRHo6z/CWaHvEX5"},"cardTxtX8_B":{"__uuid__":"b7pXy0exVFmKBQj2oOoj4U"},"cardTxtX6_A":{"__uuid__":"b9nMxsGVxOb7J3j25RwV6U"},"cardTxtX8_9":{"__uuid__":"c8bLd5AhFBGJsyCWwaqILz"},"cardTxtX4_9":{"__uuid__":"ce7wOjicJJIK04buqYMsvp"},"cardTxtX4_A":{"__uuid__":"d1KRem+ZJK278fF6o+C03y"},"cardTxtX2_B":{"__uuid__":"137GsC3UlHC7OP5ZY5toQx"},"cardTxtX36_A":{"__uuid__":"d3qSHtOhNAspELOi6XyXmo"},"cardTxtX37_5":{"__uuid__":"3bnN4KHBxCu4WTHMghZ4YH"},"cardTxtX8_C":{"__uuid__":"89jS3O/jhAp5Ws9xwHG1L9"},"cardTxtX7_D":{"__uuid__":"97zEgYZd5PkJtXtv+/F39H"},"cardTxtX40_D":{"__uuid__":"bfENGsFSdE5bFSkk1Kr6Bv"},"cardTxtX37_4":{"__uuid__":"0fT3XVlR5LCbE6LRwojTTE"},"cardTxtX4_C":{"__uuid__":"e96OSseMNKbq7lJdlyRroB"},"cardTxtX7_4":{"__uuid__":"f2yOs0dhJFNJ2yPmXr9YKh"},"cardTxtX17_F":{"__uuid__":"61AYeMmE5FZqiI+TnUCftO"},"cardTxtX17_E":{"__uuid__":"75A8t0D5BKSrlDvaIx2QD5"},"cardTxtX23_B":{"__uuid__":"7e2UCaJEVGA4wd8tSwEdlt"},"cardTxtX24_A":{"__uuid__":"99WRXlAYJCbpxsYIiVJG+6"},"cardTxtX24_5":{"__uuid__":"c8MzXOpD5EP71UeMPakmz4"},"cardTxtX21_9":{"__uuid__":"4eX5dKTGVJxITHV1r18P5F"},"cardTxtX21_6":{"__uuid__":"50DkKRD4lGcoWCByX+goMq"},"cardTxtX38_B":{"__uuid__":"09eu8BZipJ1biuRw+T/Sh2"},"cardTxtX3_8":{"__uuid__":"12n9XENIlMl4zVp3c5A3T/"},"cardTxtX5_6":{"__uuid__":"1dtGZBLfFIG4JDWJ9EuyF7"},"cardTxtX3_9":{"__uuid__":"2eiLa1XHBHwonRgOKmCW6x"},"cardTxtX4_B":{"__uuid__":"32sJqBHBtPPpzr5Wvlwczv"},"cardTxtX37_B":{"__uuid__":"3e2R1mTE5JZJjiY902vPi6"},"cardTxtX9_E":{"__uuid__":"38mI/+W+1Gj6Iir4HDtMgr"},"cardTxtX33_2":{"__uuid__":"caeomxxZ9DlK1d0bubGDoR"},"cardTxtX9_9":{"__uuid__":"417tqmfX1GE6AHlr3f+bDh"},"cardTxtX5_9":{"__uuid__":"45Hig96qBLQ6lN+koLyQKi"},"cardTxtX3_A":{"__uuid__":"50D6dQuqxAc5bQ31D5/Nu/"},"cardTxtX34_2":{"__uuid__":"373rplOiBNoKSPJjn/VjmO"},"cardTxtX6_B":{"__uuid__":"524g2i/KpMFY1HNtnVGKAS"},"cardTxtX9_8":{"__uuid__":"5ch9kuJEhCo5tZJZAVDrpx"},"cardTxtX4_6":{"__uuid__":"61Ap6c5cdMaZj0sQf2QUCy"},"cardTxtX9_6":{"__uuid__":"88MMggeslAaJhAE1EqiLfW"},"cardTxtX5_4":{"__uuid__":"8e2nPxujlMca2z4ZpXLYA2"},"cardTxtX25_6":{"__uuid__":"0bkqyzUZNH3YD8Gn2Lr37N"},"cardTxtX23_A":{"__uuid__":"1cgTgevM9BvJJFU5onyh8b"},"cardTxtX6_7":{"__uuid__":"9780e1JaRG166z7sIvOAje"},"cardTxtX9_F":{"__uuid__":"bcKDlCnG5OQaHB62bTwUQr"},"cardTxtX9_5":{"__uuid__":"dfbe6ZRmVFs6wNp8DensSf"},"cardTxtX9_A":{"__uuid__":"efK8jnPfZDDa490CR4xZQW"},"cardTxtX6_6":{"__uuid__":"f2ZY//bJdLCJBAubzbxJLI"},"cardTxtX2_A":{"__uuid__":"04Zd5qIeNN8queIK8qekz+"},"cardTxtX5_0":{"__uuid__":"18hzEhst9L6JzFb7mVtC7V"},"cardTxtX5_2":{"__uuid__":"2e6dbvSnpJWrdmc4SCo6jG"},"cardTxtX2_6":{"__uuid__":"31Wbg90bFBXYqMwgVXDEpL"},"cardTxtX8_D":{"__uuid__":"35mxIzXYFJz7SemKmu45vi"},"cardTxtX7_B":{"__uuid__":"59vk8wjTxLe4VtNLOUcELX"},"cardTxtX5_1":{"__uuid__":"64NwI20OJPJYedDT7yUuUE"},"cardTxtX7_5":{"__uuid__":"82rh7wFmJN3Yl5TwGiD6Oc"},"cardTxtX7_C":{"__uuid__":"c7ly2JhKRAJpr2P8DJqwLA"},"cardTxtX35_8":{"__uuid__":"e3zlyDppBJu7C4b8mN+npr"},"cardTxtX2_9":{"__uuid__":"c7tVlLE9FMU6BtIy7K2t9H"},"cardTxtX35_7":{"__uuid__":"92wegBwfJHj4YsyD8kRb7Q"},"cardTxtX23_5":{"__uuid__":"7865YYjaFDTLaF/1Vrs88w"},"cardTxtX25_9":{"__uuid__":"a5u+rFNlJFvryqsEBHk0+q"},"cardTxtX22_A":{"__uuid__":"5a09e42odFD7XZg/qQj9Rl"},"cardTxtX22_5":{"__uuid__":"9cb5dAJ6JBMpA2N0JnVvKl"},"cardTxtX1_4":{"__uuid__":"08cWTelyZL7YLHe91V4xNX"},"cardTxtX38_4":{"__uuid__":"20T/Oeuv9EULsr2OMfnjyv"},"cardTxtX1_F":{"__uuid__":"81SZZXHXFAFrEOL1/bhvBd"},"cardTxtX38_A":{"__uuid__":"96xoF7apBGyZtddN4O/6L0"},"cardTxtX1_D":{"__uuid__":"d1Nm61sHJNi6E6vD9vBqn0"},"cardTxtX1_E":{"__uuid__":"e9Hjy1pw1NCaakW1cqC/w5"},"cardTxtX3_7":{"__uuid__":"28qG7E581Gy6xv+DXmnaGb"},"cardTxtX5_5":{"__uuid__":"3dS1J2XxhGNpmqSb2ry2Wu"},"cardTxtX9_7":{"__uuid__":"bav3jkJYRGC5VAEuAi5uFn"},"cardTxtX6_8":{"__uuid__":"cdeRNxdp9PooFuy6cquWFH"},"cardTxtX37_A":{"__uuid__":"03g7jTxvNC/qJlBpAP/ZiL"},"cardTxtX36_9":{"__uuid__":"99iBPB1YNJVYHJ1safn0jA"},"cardTxtX36_6":{"__uuid__":"e2hTc3sqZEQJiL+gNEbfdq"},"cardTxtX38_5":{"__uuid__":"721+gABUJEep6PIh1njubs"},"cardTxtX7_E":{"__uuid__":"02OgRvfnlMFLomDJ+XVRxv"},"cardTxtX7_A":{"__uuid__":"134+H2NTVGMpp2RWZAR0kS"},"cardTxtX8_7":{"__uuid__":"14JT+DuahH5qBs7hDeUadD"},"cardTxtX7_9":{"__uuid__":"18/GMKCqhDbLmMXR0PewwS"},"cardTxtX24_6":{"__uuid__":"6dLC5sPGBGYYT00vo8/dlx"},"cardTxtX23_9":{"__uuid__":"fetUv+UVtPzoYfZTzR9Uo3"},"cardTxtX7_F":{"__uuid__":"24CfhYcXBPwJZFcXxxjeNG"},"cardTxtX5_8":{"__uuid__":"2cdxbw4RdDSpiOfCITUZr4"},"cardTxtX40_C":{"__uuid__":"34LF90mZ9NjJ9ME+XvvuC2"},"cardTxtX7_6":{"__uuid__":"34rX0zpMFMgbiulT8M1Lwo"},"cardTxtX40_3":{"__uuid__":"36cMQnaCFKhqk9NP5a191q"},"cardTxtX7_8":{"__uuid__":"84RXFoGX1H847v7ChkhAx1"},"cardTxtX5_3":{"__uuid__":"a9GsV7aGRHk6BrX3xbIT2e"},"cardTxtX4_8":{"__uuid__":"d7pBc0krlHPrpaNLqIXf83"},"cardTxtX4_7":{"__uuid__":"f98wGD4gpKyKFj4/2y1mWt"},"cardTxtX40_B":{"__uuid__":"28RrxHJxtEIp0iucd+cRYH"},"cardTxtX40_4":{"__uuid__":"ddXY9YU7lALbrAGQN06vSj"},"cardTxtX7_7":{"__uuid__":"2760iK319CKaXLy+ir9eOF"},"cardTxtX37_9":{"__uuid__":"71MzxSg25MrZP4eRAnT5Lv"},"cardTxtX8_E":{"__uuid__":"334Ueoy8JOhLScJ9T9GJ1G"},"cardTxtX35_6":{"__uuid__":"8dOfkEnbBFfo1jtSCKC9fJ"},"cardTxtX8_8":{"__uuid__":"42O/V4t4tOra6lcN2ntz/j"},"cardTxtX5_7":{"__uuid__":"c00nlcRlRIno4YTwsQxX1i"},"cardTxtX8_F":{"__uuid__":"c4IcrhhNNMfaXIefO96jrp"},"cardTxtX33_4":{"__uuid__":"48r1JcFLJDaL4rNclP2072"},"cardTxtX2_8":{"__uuid__":"2dj1HLDzhNB4zXTTdTZZw+"},"cardTxtX2_7":{"__uuid__":"e9m33nmaBPq7aDoH1WLBZc"},"cardTxtX24_9":{"__uuid__":"31aQ/xhtBFw5qcDb3qcRtp"},"cardTxtX23_6":{"__uuid__":"85pWx9S3BGw506YCLS6RQO"},"cardTxtX20_0":{"__uuid__":"07FMXqp/xLTKZtpyQ/svAA"},"cardTxtX22_9":{"__uuid__":"29NB6ajA1MErU82rUgZXOu"},"cardTxtX20_1":{"__uuid__":"43YyaH30pDbYnNOlgHW6E7"},"cardTxtX20_E":{"__uuid__":"4dkVP0NZJK5q8C7OI9S5vZ"},"cardTxtX20_F":{"__uuid__":"5fkVEo8Z5AmblCzopLxWYE"},"cardTxtX22_6":{"__uuid__":"bf3T4go3lPRrL6HEd+IJeu"},"cardTxtX1_5":{"__uuid__":"4e0TbSJVBKC4tDM5ZluY+B"},"cardTxtX1_C":{"__uuid__":"59clZ6D1RAbp5kHey2ciOT"},"cardTxtX20_2":{"__uuid__":"74y9e8qzJPo5buMDEhBw6K"},"cardTxtX37_6":{"__uuid__":"bbtz2KWLNH4ZuWSNhVxgp2"},"cardTxtX20_D":{"__uuid__":"a8KkRfFHVFr6lrYeZeAeeG"},"cardTxtX21_8":{"__uuid__":"c9cZ7d6+xIH7dOgcKQfnRe"},"cardTxtX35_5":{"__uuid__":"ed6zU1EzlKMoZKqvY7f5IV"},"cardTxtX35_3":{"__uuid__":"9cIPjLR7FMJpzDeEvOa0zx"},"cardTxtX38_9":{"__uuid__":"9aFU8Cy8NMsKqM+By+WZdN"},"cardTxtX38_6":{"__uuid__":"9dfg2nn3BJg4WoPI6VygYI"},"cardTxtX40_A":{"__uuid__":"0bsNP3jPJLVKaZsZMReauH"},"cardTxtX40_5":{"__uuid__":"84z5sRd11Aopd+TZ51TVjg"},"cardTxtX25_8":{"__uuid__":"99p2CJOiRDToRHhyKmAJ+o"},"cardTxtX20_7":{"__uuid__":"a3Ro7AzSpOmISi9VKaAciQ"},"cardTxtX23_8":{"__uuid__":"9bSdna+a9Ok4pl378OXqap"},"cardTxtX25_7":{"__uuid__":"bew2HiO21AqLVzhyYLdSCp"},"cardTxtX23_7":{"__uuid__":"e9QX4bkaJA5o2FHNOQD655"},"cardTxtX34_5":{"__uuid__":"286OI94WtJopkQtdNngqgx"},"cardTxtX21_7":{"__uuid__":"e2xRejakBLRqBb1cUf4LXI"},"cardTxtX1_6":{"__uuid__":"78VdYHjCVGJbRUEqaPxdlq"},"cardTxtX1_B":{"__uuid__":"eeqqcFoAhJH6Z1TegN6GRQ"},"cardTxtX24_8":{"__uuid__":"6cQYwjEK5IWJLRFIdUgZ4F"},"cardTxtX35_2":{"__uuid__":"b9YFOEOjdN94xAG50wBRf7"},"cardTxtX20_C":{"__uuid__":"89zf3K20lIiq11/n3OPbGh"},"cardTxtX20_3":{"__uuid__":"e4N9U47mlLTqlPc4T5EQgh"},"cardTxtX36_7":{"__uuid__":"0403Zt1iNFvZD+nfUNxQ4D"},"cardTxtX36_8":{"__uuid__":"3bEciG0KNNOKRcmyMzIA8K"},"cardTxtX35_4":{"__uuid__":"6fc8p/579Ja5boDyB+0ROx"},"cardTxtX1_A":{"__uuid__":"02IFDIiuhBSpH5i4JCsFfA"},"cardTxtX40_6":{"__uuid__":"13hzcRFWBKRIPn3BZ2CONN"},"cardTxtX37_7":{"__uuid__":"5eUBUd/2BDlafOuoXv/yvN"},"cardTxtX1_8":{"__uuid__":"25dILyChNEiJA5ZgFaPCYC"},"cardTxtX1_9":{"__uuid__":"28Y977mMJA9aQMAEOHy93T"},"cardTxtX40_9":{"__uuid__":"a3ImOXbPBORI2TC3VOL2q/"},"cardTxtX19_2":{"__uuid__":"6ewj313oRMAZR0uycVlvi7"},"cardTxtX19_D":{"__uuid__":"d6iofymfFNlZo22faZVZmt"},"cardTxtX38_7":{"__uuid__":"1003XzcAZPfbRaFKtdiQI1"},"cardTxtX22_8":{"__uuid__":"06dd5wb9pC0pXdrL23yCnF"},"cardTxtX19_3":{"__uuid__":"17qSk+G7lOBL2pQhItBN71"},"cardTxtX19_1":{"__uuid__":"2bgWToOltGh71zH1eK//gR"},"cardTxtX19_0":{"__uuid__":"3dD2Ry3xpMNIAS/mlcEE7B"},"cardTxtX22_7":{"__uuid__":"46oVwEjzlMxL7QmdN7EY1a"},"cardTxtX19_E":{"__uuid__":"56YzZZyhpKQKdZOqV7nvzo"},"cardTxtX19_F":{"__uuid__":"a5/wlp2mZD46ukmZuaqerD"},"cardTxtX37_8":{"__uuid__":"48Qh5uYQpKUKJnf9zhwJ9G"},"cardTxtX1_7":{"__uuid__":"e6PLRD1gVPrqbZrj0lUoAK"},"cardTxtX38_8":{"__uuid__":"73U7Xk3+xL7akoitSX4u/b"},"cardTxtX20_B":{"__uuid__":"117LSJRklL6JLzuZuiVCOq"},"cardTxtX20_4":{"__uuid__":"26Qr1nqr1PnoHLAPzwOi/c"},"cardTxtX19_4":{"__uuid__":"b4tTqF/vtCKJ+u0Cwsfa9M"},"cardTxtX19_C":{"__uuid__":"d7syXgKWxFZ65OiHqO6s59"},"cardTxtX19_B":{"__uuid__":"ea0P1TjH1BoJdsTaFdMh1j"},"cardTxtX34_1":{"__uuid__":"17eolYfBZM+6p8ffYwuXoy"},"cardTxtX35_1":{"__uuid__":"11sSaoyL9MB6f/1FEHtkCo"},"cardTxtX35_0":{"__uuid__":"52Jzi4NF5KLZOC/0p8T8Gk"},"cardTxtX19_A":{"__uuid__":"426T+iZ8dFS71bfSD56pIH"},"cardTxtX19_5":{"__uuid__":"d51HS6oQ9EzY/qIEJEmZon"},"cardTxtX20_5":{"__uuid__":"d7ThiXmGBGrLyXUT08XXDU"},"cardTxtX19_9":{"__uuid__":"59hfbvTslGZ6kV8tailIFT"},"cardTxtX19_6":{"__uuid__":"a36PZfglRBBZ/xs9e+zXDc"},"cardTxtX20_A":{"__uuid__":"b88MWDbuZOj5IaWt/OR0m5"},"cardTxtX33_6":{"__uuid__":"c4pAeSulBI+58zxxNEEXI+"},"cardTxtX33_5":{"__uuid__":"ccBWaKrGtKA51TREAAh0Mi"},"cardTxtX33_9":{"__uuid__":"f7Kwb6XsRMK7Ru9iV83rdN"},"cardTxtX33_D":{"__uuid__":"4eIzDV4/VBlJXVcSnOsnLS"},"cardTxtX40_7":{"__uuid__":"e8n60buyNEnLIBpvK0xHG2"},"cardTxtX33_8":{"__uuid__":"08exucC9pICImbsvQfjFes"},"cardTxtX33_7":{"__uuid__":"1cZixNO2FIT6xdk85f7sKC"},"cardTxtX33_1":{"__uuid__":"37ynVVC5tFipx8UYE1AfZn"},"cardTxtX40_8":{"__uuid__":"0bO4JpkwFGPajZxvOOihtt"},"cardTxtX19_7":{"__uuid__":"2a07t237lILJoZkOPKZ6jL"},"cardTxtX20_9":{"__uuid__":"40u8oz4xxDvY0i9IQT04E3"},"cardTxtX19_8":{"__uuid__":"49TMzIOhJKsIIwjWL2GBEM"},"cardTxtX20_6":{"__uuid__":"f3dfjtKwRD65c48GnIcTpE"},"cardTxtX33_0":{"__uuid__":"a3A0YzQypCTYBBQFlA46qd"},"cardTxtX33_E":{"__uuid__":"c1plyoaTRHT6greeXNby8c"},"cardTxtX33_F":{"__uuid__":"f5h/oAfwpCcI2+NUmHYNcT"},"cardTxtX34_E":{"__uuid__":"a4mBZJQtZA0Jxp50ITYkOq"},"cardTxtX34_F":{"__uuid__":"bcxgXAt0xFg425AbEb1SdJ"},"cardTxtX34_0":{"__uuid__":"edSRdh7NRIM77FMzlSkyhY"},"cardTxtX34_D":{"__uuid__":"7bdVTJweZPE74c2D8ioMSj"},"cardTxtX34_C":{"__uuid__":"8dBRUDYc5PCa96wws8LcDd"},"cardTxtX34_3":{"__uuid__":"9bSkiKID9P7aWd6naMWuaC"},"cardTxtX34_B":{"__uuid__":"cawSylOxxHtI8Vb/AWG1jY"},"cardTxtX34_4":{"__uuid__":"dbd9uyzvFJJKIJpprBXsj0"},"cardTxtX34_A":{"__uuid__":"b90IwuEsZDpocx5S7f7N3j"},"cardTxtX34_6":{"__uuid__":"7bqUz1cCJFdptT3iZJlTtx"},"cardTxtX34_9":{"__uuid__":"b16bA/l3tJMaLrX7ymzYs5"},"cardTxtX34_8":{"__uuid__":"baBqCiXrRDTLKCiXxu3IHo"}}}